examples/basic_inference.py
examples/clarity_api_integration.py
examples/clarity_integration.py
examples/ecommerce_session.py
examples/explain_intent.py
istari/__init__.py
istari/exceptions.py
istari/agents/base.py
istari/agents/clarity_insights_agent.py
istari/core/__init__.py
istari/core/events.py
istari/core/explain.py
istari/core/intent_state.py
istari/core/scoring.py
istari/core/session.py
istari/core/timeline.py
istari/core/transition.py
istari/explainability/__init__.py
istari/explainability/attributions.py
istari/explainability/narratives.py
istari/explainability/summaries.py
istari/inference/__init__.py
istari/inference/confidence.py
istari/inference/heuristics.py
istari/inference/rules.py
istari/inference/state_machine.py
istari/integrations/__init__.py
istari/integrations/amplitude.py
istari/integrations/generic.py
istari/integrations/mixpanel.py
istari/integrations/segment.py
istari/plugins/__init__.py
istari/plugins/base.py
istari/plugins/registry.py
istari/schemas/__init__.py
istari/schemas/base.py
istari/schemas/ecommerce.py
istari/schemas/web.py
istari/signals/__init__.py
istari/signals/comparison.py
istari/signals/dwell.py
istari/signals/friction.py
istari/signals/navigation.py
istari/signals/price.py
istari/sources/__init__.py
istari/sources/base.py
istari/sources/clarity/__init__.py
istari/sources/clarity/api_client.py
istari/sources/clarity/mapper.py
istari/sources/clarity/parser.py
istari/sources/clarity/schema.py
istari/sources/clarity/source.py
istari/utils/__init__.py
istari/utils/math.py
istari/utils/time.py
istari/utils/validation.py
istari_core-0.1.2.dist-info/licenses/LICENSE
rough/test_clarity_ingestion.py
tests/__init__.py
tests/verify_installation.py
tests/core/__init__.py
tests/explainability/__init__.py
tests/inference/__init__.py
tests/signals/__init__.py
istari_core-0.1.2.dist-info/METADATA
istari_core-0.1.2.dist-info/WHEEL
istari_core-0.1.2.dist-info/top_level.txt
istari_core-0.1.2.dist-info/RECORD
