Metadata-Version: 2.4
Name: istari-core
Version: 0.1.2
Summary: Infer user intent states from behavioral event streams
Author: Tanay Agrawal
License: Apache-2.0
Project-URL: Homepage, https://github.com/istari/istari
Project-URL: Documentation, https://github.com/istari/istari/docs
Project-URL: Repository, https://github.com/istari/istari
Project-URL: Issues, https://github.com/istari/istari/issues
Keywords: intent,analytics,behavior,cro,personalization,ai
Classifier: Development Status :: 3 - Alpha
Classifier: Intended Audience :: Developers
Classifier: License :: OSI Approved :: Apache Software License
Classifier: Programming Language :: Python :: 3
Classifier: Programming Language :: Python :: 3.8
Classifier: Programming Language :: Python :: 3.9
Classifier: Programming Language :: Python :: 3.10
Classifier: Programming Language :: Python :: 3.11
Classifier: Programming Language :: Python :: 3.12
Classifier: Topic :: Software Development :: Libraries :: Python Modules
Classifier: Topic :: Scientific/Engineering :: Artificial Intelligence
Requires-Python: >=3.8
License-File: LICENSE
Provides-Extra: dev
Requires-Dist: pytest>=7.0; extra == "dev"
Requires-Dist: pytest-cov>=4.0; extra == "dev"
Requires-Dist: black>=23.0; extra == "dev"
Requires-Dist: ruff>=0.1.0; extra == "dev"
Requires-Dist: mypy>=1.0; extra == "dev"
Dynamic: license-file
